{
  "_id": "f0cd817434c10827",
  "name": "Electronic Counter-Countermeasures (ECCM)",
  "type": "vehicle_mod",
  "img": "icons/svg/upgrade.svg",
  "system": {
    "modType": "electronics",
    "rating": 10,
    "cost": 10000,
    "installed": false,
    "notes": "Signal amplifiers and noise filters that nullify enemy ECM (generally more available than ECM). Leveled 1–10; weight 12 kg (L1) up to 250 kg (L10); Base Time 16 hrs/level; Avail 4/7 days (L1) up to 18/1 year (L10). NOTE: the per-level Customization Cost column is garbled in the scan (L1 reads 110,000¥, inconsistent with L2 30,000¥) — costs flagged in NEEDS-CAPTURE pending a clean capture; the 10,000¥ here is a placeholder. Rigger 2 p.138."
  },
  "effects": [],
  "flags": {},
  "folder": null,
  "sort": 0,
  "_stats": {
    "coreVersion": "13.351",
    "systemId": "sr2e",
    "systemVersion": "0.0.1",
    "createdTime": 1781600000000,
    "modifiedTime": 1781600000000,
    "lastModifiedBy": null,
    "compendiumSource": null,
    "duplicateSource": null,
    "exportSource": null
  },
  "ownership": {
    "default": 0
  },
  "_key": "!items!f0cd817434c10827"
}
