{
  "_id": "f1ea71293c020c76",
  "name": "Signal Amplifier",
  "type": "gear",
  "img": "icons/svg/upgrade.svg",
  "system": {
    "category": "electronics",
    "rating": 1,
    "quantity": 1,
    "weight": 1,
    "cost": 250,
    "availability": "(Rating)/(Rating × 12) hours",
    "legality": "Legal",
    "equipped": false,
    "concealability": 0,
    "weaponAccessory": false,
    "linkedWeaponId": "",
    "combatTnMod": 0,
    "accessoryRecoilComp": 0,
    "requiresSmartgun": false,
    "notes": "Boosts a remote-control signal's range (Rating 1–10). Weight = 1 × Rating kg; cost = Rating × 250¥. Street Index 1.5. Rigger 2."
  },
  "effects": [],
  "flags": {},
  "folder": null,
  "sort": 0,
  "_stats": {
    "coreVersion": "13.351",
    "systemId": "sr2e",
    "systemVersion": "0.0.1",
    "createdTime": 1781600000000,
    "modifiedTime": 1781600000000,
    "lastModifiedBy": null,
    "compendiumSource": null,
    "duplicateSource": null,
    "exportSource": null
  },
  "ownership": {
    "default": 0
  },
  "_key": "!items!f1ea71293c020c76"
}
